bobskater/frameUtils.py
bobskater/obfuscate.py
bobskater-0.2.1.dist-info/LICENSE.txt
bobskater-0.2.1.dist-info/METADATA
bobskater-0.2.1.dist-info/WHEEL
bobskater-0.2.1.dist-info/top_level.txt
bobskater-0.2.1.dist-info/RECORD
