Metadata-Version: 2.1
Name: bobskater
Version: 0.2.1
Summary: AST based Obfuscator for Python
Home-page: https://github.com/Cobertos/bobskater/
Author: Peter "Cobertos" Fornari
Author-email: cobertosrobertos@gmail.com
License: MIT
Keywords: bobskater obfuscator obfuscation minifier mangler python
Platform: UNKNOWN
Classifier: Development Status :: 3 - Alpha
Classifier: Intended Audience :: Developers
Classifier: License :: OSI Approved :: MIT License
Classifier: Programming Language :: Python :: 3.5
Classifier: Programming Language :: Python :: 3.6
Classifier: Programming Language :: Python :: 3.7
Classifier: Topic :: Software Development :: Build Tools
Classifier: Topic :: Software Development :: Code Generators
Requires-Dist: astunparse
